aws3/__init__.py
aws3/cli.py
ass_cli-0.0.1.dist-info/METADATA
ass_cli-0.0.1.dist-info/WHEEL
ass_cli-0.0.1.dist-info/entry_points.txt
ass_cli-0.0.1.dist-info/top_level.txt
ass_cli-0.0.1.dist-info/RECORD
