Metadata-Version: 2.1
Name: ass-cli
Version: 0.0.1
Summary: Serverless stack deployment tools
Home-page: UNKNOWN
Author: Pravash Raj Upreti
Author-email: pravashupreti@gmail.com
License: MIT
Keywords: cli
Platform: UNKNOWN
Classifier: Intended Audience :: Developers
Classifier: Topic :: Utilities
Classifier: License :: Public Domain
Classifier: Natural Language :: English
Classifier: Operating System :: OS Independent
Classifier: Programming Language :: Python :: 3
Requires-Dist: python-dotenv (==0.6.5)
Requires-Dist: terminaltables (==3.1.0)
Requires-Dist: click (==6.7)
Provides-Extra: test
Requires-Dist: mock ; extra == 'test'
Requires-Dist: coverage ; extra == 'test'
Requires-Dist: pytest ; extra == 'test'
Requires-Dist: pytest-cov ; extra == 'test'
Requires-Dist: pylint ; extra == 'test'
Requires-Dist: pytest-watch ; extra == 'test'
